[
  {
    "orderNo": "FS20251222053",
    "companyNameEN": "PETSOME SDN BHD",
    "companyNameCN": "",
    "invoiceType": "开票",
    "totalAmountCustomer": 141696,
    "totalAmountFactory": null,
    "invoicedAmount": 0,
    "pendingInvoice": 141696,
    "receivedInvoice": 0,
    "pendingReceive": 141696,
    "thisInvoiceAmount": 141696,
    "thisReceiveAmount": 0,
    "invoiceNo": "",
    "invoiceCode": "",
    "invoiceNumber": "",
    "invoiceDate": null,
    "invoiceTypeName": "",
    "invoiceName": "",
    "checkCode": "",
    "buyerName": "",
    "buyerTaxId": "",
    "buyerAddress": "",
    "buyerBank": "",
    "sellerName": "",
    "sellerTaxId": "",
    "sellerAddress": "",
    "sellerBankCNY": "",
    "sellerBankUSD": "",
    "sellerAccountUSD": "",
    "subtotal": null,
    "totalTax": null,
    "totalWithTaxCN": "",
    "totalWithTax": null,
    "details": [],
    "reviewer": "",
    "invoicedBy": "",
    "issuingCompany": "",
    "createTime": "2025-12-23T07:57:03.362Z",
    "updateTime": "2025-12-23T07:57:03.362Z"
  },
  {
    "orderNo": "FS20251224054",
    "companyNameEN": "PETSOME SDN BHD",
    "companyNameCN": "",
    "invoiceType": "开票",
    "totalAmountCustomer": 760140,
    "totalAmountFactory": null,
    "invoicedAmount": 0,
    "pendingInvoice": 760140,
    "receivedInvoice": 0,
    "pendingReceive": 0,
    "thisInvoiceAmount": 760140,
    "thisReceiveAmount": 0,
    "invoiceNo": "",
    "invoiceCode": "",
    "invoiceNumber": "",
    "invoiceDate": null,
    "invoiceTypeName": "",
    "invoiceName": "",
    "checkCode": "",
    "buyerName": "",
    "buyerTaxId": "",
    "buyerAddress": "",
    "buyerBank": "",
    "sellerName": "",
    "sellerTaxId": "",
    "sellerAddress": "",
    "sellerBankCNY": "",
    "sellerBankUSD": "",
    "sellerAccountUSD": "",
    "subtotal": null,
    "totalTax": null,
    "totalWithTaxCN": "",
    "totalWithTax": null,
    "details": [],
    "reviewer": "",
    "invoicedBy": "",
    "issuingCompany": "",
    "createTime": "2025-12-24T10:45:34.713Z",
    "updateTime": "2025-12-24T10:45:34.713Z"
  },
  {
    "orderNo": "FS20251225057",
    "companyNameEN": "PETSOME (EU) SDN BHD",
    "companyNameCN": "",
    "invoiceType": "开票",
    "totalAmountCustomer": 405900,
    "totalAmountFactory": 405900,
    "invoicedAmount": 0,
    "pendingInvoice": 405900,
    "receivedInvoice": 0,
    "pendingReceive": 405900,
    "thisInvoiceAmount": 300020,
    "thisReceiveAmount": 0,
    "invoiceNo": "",
    "invoiceCode": "",
    "invoiceNumber": "",
    "invoiceDate": null,
    "invoiceTypeName": "",
    "invoiceName": "",
    "checkCode": "",
    "buyerName": "",
    "buyerTaxId": "",
    "buyerAddress": "",
    "buyerBank": "",
    "sellerName": "",
    "sellerTaxId": "",
    "sellerAddress": "",
    "sellerBankCNY": "",
    "sellerBankUSD": "",
    "sellerAccountUSD": "",
    "subtotal": null,
    "totalTax": null,
    "totalWithTaxCN": "",
    "totalWithTax": null,
    "details": [],
    "reviewer": "",
    "invoicedBy": "",
    "issuingCompany": "厦门巴匕进出口有限公司",
    "createTime": "2025-12-26T10:37:45.094Z",
    "updateTime": "2025-12-26T10:37:45.094Z"
  },
  {
    "orderNo": "FS20251225057",
    "companyNameEN": "PETSOME (EU) SDN BHD",
    "companyNameCN": "",
    "invoiceType": "收票",
    "totalAmountCustomer": 405900,
    "totalAmountFactory": 405900,
    "invoicedAmount": 300020,
    "pendingInvoice": 105880,
    "receivedInvoice": 0,
    "pendingReceive": 405900,
    "thisInvoiceAmount": 0,
    "thisReceiveAmount": 405900,
    "invoiceNo": "",
    "invoiceCode": "",
    "invoiceNumber": "",
    "invoiceDate": null,
    "invoiceTypeName": "",
    "invoiceName": "",
    "checkCode": "",
    "buyerName": "",
    "buyerTaxId": "",
    "buyerAddress": "",
    "buyerBank": "",
    "sellerName": "",
    "sellerTaxId": "",
    "sellerAddress": "",
    "sellerBankCNY": "",
    "sellerBankUSD": "",
    "sellerAccountUSD": "",
    "subtotal": null,
    "totalTax": null,
    "totalWithTaxCN": "",
    "totalWithTax": null,
    "details": [],
    "reviewer": "",
    "invoicedBy": "",
    "issuingCompany": "厦门巴匕进出口有限公司",
    "createTime": "2025-12-26T10:38:28.914Z",
    "updateTime": "2025-12-26T10:38:28.914Z"
  },
  {
    "orderNo": "FS20251226058",
    "companyNameEN": "PETSOME (EU) SDN BHD",
    "companyNameCN": "",
    "invoiceType": "开票",
    "totalAmountCustomer": 7380,
    "totalAmountFactory": 7380,
    "invoicedAmount": 0,
    "pendingInvoice": 7380,
    "receivedInvoice": 0,
    "pendingReceive": 7380,
    "thisInvoiceAmount": 7380,
    "thisReceiveAmount": 0,
    "invoiceNo": "",
    "invoiceCode": "",
    "invoiceNumber": "",
    "invoiceDate": null,
    "invoiceTypeName": "",
    "invoiceName": "",
    "checkCode": "",
    "buyerName": "",
    "buyerTaxId": "",
    "buyerAddress": "",
    "buyerBank": "",
    "sellerName": "",
    "sellerTaxId": "",
    "sellerAddress": "",
    "sellerBankCNY": "",
    "sellerBankUSD": "",
    "sellerAccountUSD": "",
    "subtotal": null,
    "totalTax": null,
    "totalWithTaxCN": "",
    "totalWithTax": null,
    "details": [],
    "reviewer": "",
    "invoicedBy": "",
    "issuingCompany": "厦门巴匕进出口有限公司",
    "createTime": "2025-12-26T10:48:15.905Z",
    "updateTime": "2025-12-26T10:48:15.905Z"
  },
  {
    "orderNo": "FS20251226058",
    "companyNameEN": "PETSOME (EU) SDN BHD",
    "companyNameCN": "",
    "invoiceType": "收票",
    "totalAmountCustomer": 7380,
    "totalAmountFactory": 7380,
    "invoicedAmount": 7380,
    "pendingInvoice": 0,
    "receivedInvoice": 0,
    "pendingReceive": 7380,
    "thisInvoiceAmount": 0,
    "thisReceiveAmount": 7380,
    "invoiceNo": "",
    "invoiceCode": "",
    "invoiceNumber": "",
    "invoiceDate": null,
    "invoiceTypeName": "",
    "invoiceName": "",
    "checkCode": "",
    "buyerName": "",
    "buyerTaxId": "",
    "buyerAddress": "",
    "buyerBank": "",
    "sellerName": "",
    "sellerTaxId": "",
    "sellerAddress": "",
    "sellerBankCNY": "",
    "sellerBankUSD": "",
    "sellerAccountUSD": "",
    "subtotal": null,
    "totalTax": null,
    "totalWithTaxCN": "",
    "totalWithTax": null,
    "details": [],
    "reviewer": "",
    "invoicedBy": "",
    "issuingCompany": "厦门巴匕进出口有限公司",
    "createTime": "2025-12-26T10:49:01.220Z",
    "updateTime": "2025-12-26T10:49:01.220Z"
  },
  {
    "orderNo": "FS20251231065",
    "companyNameEN": "PETSOME (EU) SDN BHD",
    "companyNameCN": "",
    "invoiceType": "开票",
    "totalAmountCustomer": 184800,
    "totalAmountFactory": null,
    "invoicedAmount": 0,
    "pendingInvoice": 184800,
    "receivedInvoice": 0,
    "pendingReceive": 0,
    "thisInvoiceAmount": 184800,
    "thisReceiveAmount": 0,
    "invoiceNo": "PBTDB-20251106",
    "invoiceCode": "",
    "invoiceNumber": "",
    "invoiceDate": null,
    "invoiceTypeName": "",
    "invoiceName": "",
    "checkCode": "",
    "buyerName": "",
    "buyerTaxId": "",
    "buyerAddress": "",
    "buyerBank": "",
    "sellerName": "",
    "sellerTaxId": "",
    "sellerAddress": "",
    "sellerBankCNY": "",
    "sellerBankUSD": "",
    "sellerAccountUSD": "",
    "subtotal": null,
    "totalTax": null,
    "totalWithTaxCN": "",
    "totalWithTax": null,
    "details": [],
    "reviewer": "",
    "invoicedBy": "",
    "issuingCompany": "",
    "createTime": "2026-01-19T11:24:00.710Z",
    "updateTime": "2026-01-19T11:24:00.710Z"
  },
  {
    "orderNo": "FS20251231065",
    "companyNameEN": "PETSOME (EU) SDN BHD",
    "companyNameCN": "",
    "invoiceType": "收票",
    "totalAmountCustomer": 184800,
    "totalAmountFactory": 184800,
    "invoicedAmount": 184800,
    "pendingInvoice": 0,
    "receivedInvoice": 0,
    "pendingReceive": 184800,
    "thisInvoiceAmount": 0,
    "thisReceiveAmount": 184800,
    "invoiceNo": "25352000000134527277",
    "invoiceCode": "",
    "invoiceNumber": "",
    "invoiceDate": null,
    "invoiceTypeName": "",
    "invoiceName": "",
    "checkCode": "",
    "buyerName": "",
    "buyerTaxId": "",
    "buyerAddress": "",
    "buyerBank": "",
    "sellerName": "",
    "sellerTaxId": "",
    "sellerAddress": "",
    "sellerBankCNY": "",
    "sellerBankUSD": "",
    "sellerAccountUSD": "",
    "subtotal": null,
    "totalTax": null,
    "totalWithTaxCN": "",
    "totalWithTax": null,
    "details": [],
    "reviewer": "",
    "invoicedBy": "",
    "issuingCompany": "厦门巴匕进出口有限公司",
    "createTime": "2026-01-19T11:25:38.661Z",
    "updateTime": "2026-01-19T11:27:52.104Z"
  },
  {
    "orderNo": "FS20260123020",
    "companyNameEN": "Magros Petcare SL",
    "companyNameCN": "",
    "invoiceType": "收票",
    "totalAmountCustomer": 48502,
    "totalAmountFactory": 48502,
    "invoicedAmount": 0,
    "pendingInvoice": 48502,
    "receivedInvoice": 0,
    "pendingReceive": 48502,
    "thisInvoiceAmount": 0,
    "thisReceiveAmount": 48502,
    "invoiceNo": "",
    "invoiceCode": "",
    "invoiceNumber": "",
    "invoiceDate": null,
    "invoiceTypeName": "",
    "invoiceName": "",
    "checkCode": "",
    "buyerName": "",
    "buyerTaxId": "",
    "buyerAddress": "",
    "buyerBank": "",
    "sellerName": "",
    "sellerTaxId": "",
    "sellerAddress": "",
    "sellerBankCNY": "",
    "sellerBankUSD": "",
    "sellerAccountUSD": "",
    "subtotal": null,
    "totalTax": null,
    "totalWithTaxCN": "",
    "totalWithTax": null,
    "details": [],
    "reviewer": "",
    "invoicedBy": "",
    "issuingCompany": "厦门巴匕进出口有限公司",
    "createTime": "2026-01-23T12:12:45.770Z",
    "updateTime": "2026-01-23T12:12:45.770Z"
  }
]